[
    {
        "chainId": 1516,
        "address": "0xe8CabF9d1FFB6CE23cF0a86641849543ec7BD7d5",
        "name": "IP",
        "symbol": "IP",
        "tag": ["stnd_ip", "stnd_native"],
        "decimals": 18,
        "logoURI": "https://raw.githubusercontent.com/standardweb3/default-token-list/refs/heads/main/assets/story_iliad/IP.png"
    },
    {
        "chainId": 1516,
        "address": "0x40fCa9cB1AB15eD9B5bDA19A52ac00A78AE08e1D",
        "name": "USD Coin",
        "symbol": "USDC",
        "tag": ["stnd_usdc", "stnd_stablecoin"],
        "decimals": 6,
        "logoURI": "https://ethereum-optimism.github.io/data/USDC/logo.png"
    },
    {
        "address": "0x02F75bdBb4732cc6419aC15EeBeE6BCee66e826f",
        "chainId": 1516,
        "name": "Tether USD",
        "symbol": "USDT",
        "tag": ["stnd_usdt", "stnd_stablecoin"],
        "decimals": 6,
        "logoURI": "https://assets.coingecko.com/coins/images/325/standard/Tether.png?1696501661"
    },
    {
        "address": "0x656afb1968bC39Cf3937f68CC6089F10cf47C1F7",
        "chainId": 1516,
        "name": "Wrapped Bitcoin",
        "symbol": "WBTC",
        "tag": ["stnd_btc"],
        "decimals": 8,
        "logoURI": "https://assets.coingecko.com/coins/images/7598/standard/wrapped_bitcoin_wbtc.png?1696507857"
    },
    {
        "address": "0x1C13B2B65d55dF06FF43528E736Db2F8e372E692",
        "chainId": 1516,
        "name": "Wrapped Ether",
        "symbol": "WETH",
        "tag": ["stnd_eth"],
        "decimals": 18,
        "logoURI": "https://assets.coingecko.com/coins/images/2518/standard/weth.png?1696503332"
    }
]